maha_eo/__init__.py
maha_eo/checker.py
maha_eo-0.0.1.dist-info/METADATA
maha_eo-0.0.1.dist-info/WHEEL
maha_eo-0.0.1.dist-info/top_level.txt
maha_eo-0.0.1.dist-info/RECORD
